TopasOpt/Optimisers.py
TopasOpt/TopasScriptGenerator.py
TopasOpt/__init__.py
TopasOpt/utilities.py
topasopt-1.0.1.dist-info/LICENSE.md
topasopt-1.0.1.dist-info/METADATA
topasopt-1.0.1.dist-info/WHEEL
topasopt-1.0.1.dist-info/RECORD
