Metadata-Version: 2.1
Name: topasopt
Version: 1.0.1
Summary: 
License: MIT
Author: brendan whelan
Requires-Python: >=3.9,<4.0
Classifier: License :: OSI Approved :: MIT License
Classifier: Programming Language :: Python :: 3
Classifier: Programming Language :: Python :: 3.9
Classifier: Programming Language :: Python :: 3.10
Classifier: Programming Language :: Python :: 3.11
Classifier: Programming Language :: Python :: 3.12
Classifier: Programming Language :: Python :: 3.13
Requires-Dist: bayesian-optimization (>=2.0.0,<3.0.0)
Requires-Dist: jsonpickle (>=4.0.0,<5.0.0)
Requires-Dist: matplotlib (>=3.9.2,<4.0.0)
Requires-Dist: numpy (>=1.25)
Requires-Dist: scikit-learn (>=1.0.0,<2.0.0)
Requires-Dist: scipy (>=1.0.0,<2.0.0)
Requires-Dist: topas2numpy (>=0.2.0,<0.3.0)
